payselection/__init__.py
payselection/core/__init__.py
payselection/core/client.py
payselection/core/configuration.py
payselection/core/enums.py
payselection/core/service.py
payselection/core/urls.py
payselection/core/exceptions/__init__.py
payselection/core/exceptions/api_error.py
payselection/core/exceptions/webhook.py
payselection/core/schemas/__init__.py
payselection/core/schemas/recurring.py
payselection/core/schemas/schema.py
payselection/core/schemas/receipt/__init__.py
payselection/core/schemas/receipt/ffd1_05.py
payselection/core/schemas/receipt/ffd1_2.py
payselection/core/schemas/receipt/item.py
payselection/core/schemas/receipt/receipt_data.py
payselection/core/utils/__init__.py
payselection/core/utils/cryptogram_formation.py
payselection/core/utils/currency_code.py
payselection/core/utils/signature_formation.py
payselection/gateway_payment/__init__.py
payselection/gateway_payment/enums.py
payselection/gateway_payment/services.py
payselection/gateway_payment/schemas/__init__.py
payselection/gateway_payment/schemas/card_data.py
payselection/gateway_payment/schemas/pay.py
payselection/gateway_payment/schemas/payout.py
payselection/gateway_payment/schemas/schema.py
payselection/recurring/__init__.py
payselection/recurring/enum.py
payselection/recurring/schema.py
payselection/recurring/services.py
payselection/web_payment/__init__.py
payselection/web_payment/schema.py
payselection/web_payment/services.py
payselection/webhook/__init__.py
payselection/webhook/services.py
payselection/webhook/payment/__init__.py
payselection/webhook/payment/enum.py
payselection/webhook/payment/schema.py
payselection/webhook/recurring/__init__.py
payselection/webhook/recurring/enum.py
payselection/webhook/recurring/schema.py
payselection-1.0.3.dist-info/LICENSE
payselection-1.0.3.dist-info/METADATA
payselection-1.0.3.dist-info/WHEEL
payselection-1.0.3.dist-info/top_level.txt
payselection-1.0.3.dist-info/RECORD
