Metadata-Version: 2.1
Name: payselection
Version: 1.0.3
Summary: Payselection SDK allows you to integrate work with payments for applications
Author-email: Rudenkov Vadim <vadzim.r@gofarsoft.org>
Project-URL: Homepage, https://github.com/Payselection/Payselection-PayApp-SDK-Python
Project-URL: Issues, https://github.com/Payselection/Payselection-PayApp-SDK-Python/issues
Classifier: Programming Language :: Python :: 3
Classifier: Operating System :: OS Independent
Classifier: License :: OSI Approved :: MIT License
Requires-Python: >=3.7
License-File: LICENSE
Requires-Dist: requests
Requires-Dist: pydantic ==2.5.3
Requires-Dist: pydantic-settings ==2.0.3
Requires-Dist: cryptography
Requires-Dist: email-validator
Requires-Dist: setuptools
Requires-Dist: urllib3
Requires-Dist: python-dateutil
Requires-Dist: langcodes
Requires-Dist: pydantic-extra-types
Requires-Dist: pycountry
